<?xml version="1.0" encoding="UTF-8"?>
<features xmlns="http://karaf.apache.org/xmlns/features/v1.2.0" name="Tactix4">
    <feature name="Tactix4 ADT" version="1.0">
        <feature>spring</feature>
        <feature version="2.12.2">camel-scala</feature>
        <feature version="2.12.2">camel-hl7</feature>
		<feature version="2.12.2">camel-mina2</feature>
		<feature version="2.12.2">camel-spring</feature>
        <bundle>mvn:org.scalaz/scalaz-core_2.10/7.0.3</bundle>
        <bundle>mvn:org.scalaz/scalaz-concurrent_2.10/7.0.3</bundle>
        <bundle>mvn:org.scalaz/scalaz-effect_2.10/7.0.3</bundle>
        <bundle>wrap:mvn:com.typesafe/scalalogging-slf4j_2.10/1.0.1</bundle>
        <bundle>mvn:com.ning/async-http-client/1.7.16</bundle>
        <bundle>wrap:mvn:net.databinder.dispatch/dispatch-core_2.10/0.11.0</bundle>
        <bundle>mvn:joda-time/joda-time/2.3</bundle>
        <bundle>mvn:io.netty/netty/3.6.3.Final</bundle>
        <bundle>wrap:mvn:org.springframework.scala/spring-scala_2.10/1.0.0.RC1</bundle>
        <bundle>mvn:com.tactix4/t4xmlrpc_2.10/1.1-SNAPSHOT</bundle>
        <bundle>mvn:com.tactix4/t4openerp-connector_2.10/1.2-SNAPSHOT</bundle>
        <bundle>mvn:com.tactix4/t4skr-core_2.10/1.0-SNAPSHOT</bundle>
        <bundle>mvn:com.tactix4/t4skr-connector_2.10/1.0-SNAPSHOT</bundle>
        <bundle>mvn:com.codahale.metrics/metrics-core/3.0.1</bundle>
        <bundle>mvn:com.codahale.metrics/metrics-healthchecks/3.0.1</bundle>
        <bundle>wrap:mvn:nl.grons/metrics-scala_2.10/3.0.4</bundle>
        <bundle>mvn:com.tactix4/t4adt_2.10/0.0.1-SNAPSHOT</bundle>
   </feature>

</features>
